chroma_dp/__init__.py
chroma_dp/chroma/__init__.py
chroma_dp/chroma/chroma_export.py
chroma_dp/chroma/chroma_import.py
chroma_dp/huggingface/__init__.py
chroma_dp/huggingface/utils.py
chroma_dp/main.py
chroma_dp/processor/__init__.py
chroma_dp/processor/chunk.py
chroma_dp/processor/embed.py
chroma_dp/processor/id.py
chroma_dp/processor/langchain_utils.py
chroma_dp/processor/metadata.py
chroma_dp/processor/misc/__init__.py
chroma_dp/processor/misc/emoji_clean.py
chroma_dp/producer/__init__.py
chroma_dp/producer/file/__init__.py
chroma_dp/producer/file/csv.py
chroma_dp/producer/file/pdf.py
chroma_dp/producer/file/text.py
chroma_dp/producer/langchain/__init__.py
chroma_dp/producer/url/__init__.py
chroma_dp/producer/url/url_loader.py
chroma_dp/utils/__init__.py
chroma_dp/utils/chroma.py
chroma_dp/utils/embedding.py
chroma_dp/utils/templating.py
chromadb_data_pipes-0.0.12.dist-info/LICENSE.md
chromadb_data_pipes-0.0.12.dist-info/METADATA
chromadb_data_pipes-0.0.12.dist-info/WHEEL
chromadb_data_pipes-0.0.12.dist-info/entry_points.txt
chromadb_data_pipes-0.0.12.dist-info/RECORD
