Metadata-Version: 2.1
Name: chromadb-data-pipes
Version: 0.0.12
Summary: Chroma Data Pipes 🖇️ - The easiest way to get data into and out of ChromaDB
License: MIT
Author: Trayan Azarov
Author-email: trayan.azarov@amikos.tech
Requires-Python: >=3.9,<3.12
Classifier: License :: OSI Approved :: MIT License
Classifier: Programming Language :: Python :: 3
Classifier: Programming Language :: Python :: 3.9
Classifier: Programming Language :: Python :: 3.10
Classifier: Programming Language :: Python :: 3.11
Requires-Dist: chromadb (>=0.4.0,<0.6.0)
Requires-Dist: datasets (>=2.15.0,<3.0.0)
Requires-Dist: essential-generators (>=1.0,<2.0)
Requires-Dist: fastapi (>=0.108,<0.110)
Requires-Dist: langchain (>=0.1,<0.3)
Requires-Dist: orjson (>=3.9.12,<4.0.0)
Requires-Dist: py-ulid (>=1.0.3,<2.0.0)
Requires-Dist: pydantic (>=2.5.3,<3.0.0)
Requires-Dist: pypdf (>=3.17.4,<4.0.0)
Requires-Dist: python-dotenv (>=1.0.1,<2.0.0)
Requires-Dist: rich (>=13.7.0,<14.0.0)
Requires-Dist: tenacity (>=8.2.3,<9.0.0)
Requires-Dist: tqdm (>=4.66.1,<5.0.0)
Requires-Dist: typer[all] (>=0.9.0,<0.10.0)
Project-URL: Bug Tracker, https://github.com/amikos-tech/chromadb-data-pipes/issues
Project-URL: Homepage, https://datapipes.chromadb.dev/
Project-URL: Source, https://github.com/amikos-tech/chromadb-data-pipes/
